pystarport/__init__.py
pystarport/app.py
pystarport/bot.py
pystarport/cli.py
pystarport/cluster.py
pystarport/convert.sh
pystarport/cosmoscli.py
pystarport/default.nix
pystarport/expansion.py
pystarport/ledger.py
pystarport/ports.py
pystarport/proto_python/api_util.py
pystarport/proto_python/grpc_util.py
pystarport/tests/test_expansion/base.jsonnet
pystarport/tests/test_expansion/base.yaml
pystarport/tests/test_expansion/cronos_has_dotenv.jsonnet
pystarport/tests/test_expansion/cronos_has_dotenv.yaml
pystarport/tests/test_expansion/cronos_has_posix_no_dotenv.jsonnet
pystarport/tests/test_expansion/cronos_has_posix_no_dotenv.yaml
pystarport/tests/test_expansion/cronos_no_dotenv.jsonnet
pystarport/tests/test_expansion/cronos_no_dotenv.yaml
pystarport/tests/test_expansion/dotenv
pystarport/tests/test_expansion/dotenv1
pystarport/tests/test_expansion/test_expansion.py
pystarport/tests/test_expansion/yaml_doc.jsonnet
pystarport/utils.py
pystarport-0.2.5.dist-info/METADATA
pystarport-0.2.5.dist-info/entry_points.txt
pystarport-0.2.5.dist-info/WHEEL
pystarport-0.2.5.dist-info/LICENSE
pystarport-0.2.5.dist-info/RECORD
