Metadata-Version: 2.1
Name: pystarport
Version: 0.2.5
Summary: Spawn local devnets for cosmos-sdk chains
Home-page: https://github.com/crypto-com/pystarport
License: Apache
Keywords: CRO,blockchain,crypto.com,cosmos
Author: chain-dev-team
Author-email: chain-dev@crypto.com
Requires-Python: >=3.8,<4.0
Classifier: License :: Other/Proprietary License
Classifier: Programming Language :: Python :: 3
Classifier: Programming Language :: Python :: 3.8
Classifier: Programming Language :: Python :: 3.9
Classifier: Programming Language :: Python :: 3.10
Classifier: Programming Language :: Python :: 3.11
Requires-Dist: PyYAML (>=5.3.1,<6.0.0)
Requires-Dist: bech32 (>=1.1.0,<2.0.0)
Requires-Dist: docker (>=5.0.3,<6.0.0)
Requires-Dist: durations (>=0.3.3,<0.4.0)
Requires-Dist: fire (>=0.4.0,<0.5.0)
Requires-Dist: jsonmerge (>=1.7.0,<2.0.0)
Requires-Dist: jsonnet (>=0.18.0,<0.19.0)
Requires-Dist: multitail2 (>=1.5.2,<2.0.0)
Requires-Dist: python-dateutil (>=2.8.1,<3.0.0)
Requires-Dist: python-dotenv (>=0.19.2,<0.20.0)
Requires-Dist: pyyaml-include (>=1.3,<2.0)
Requires-Dist: supervisor (>=4.2.1,<5.0.0)
Requires-Dist: tomlkit (>=0.7.0,<0.8.0)
Project-URL: Repository, https://github.com/crypto-com/pystarport
